pybeepop/__init__.py
pybeepop/data/BeePop_exposed_parameters.csv
pybeepop/lib/beepop_linux.so
pybeepop/lib/beepop_win64.dll
pybeepop/plots.py
pybeepop/pybeepop.py
pybeepop/tools.py
pybeepop_plus-0.1.4.dist-info/LICENSE
pybeepop_plus-0.1.4.dist-info/METADATA
pybeepop_plus-0.1.4.dist-info/WHEEL
pybeepop_plus-0.1.4.dist-info/RECORD
