Metadata-Version: 2.3
Name: pybeepop-plus
Version: 0.1.4
Summary: EPA's Python interface for the EPA/USDA honey bee colony model BeePop+
License: MIT
Author: Jeffrey Minucci
Author-email: minucci.jeffrey@epa.gov
Maintainer: Jeffrey Minucci
Maintainer-email: minucci.jeffrey@epa.gov
Requires-Python: >=3.8.0,<4.0.0
Classifier: Intended Audience :: Science/Research
Classifier: License :: OSI Approved :: MIT License
Classifier: Operating System :: Microsoft :: Windows
Classifier: Operating System :: POSIX :: Linux
Classifier: Programming Language :: Python
Classifier: Programming Language :: Python :: 3
Classifier: Programming Language :: Python :: 3.8
Classifier: Programming Language :: Python :: 3.9
Classifier: Programming Language :: Python :: 3.10
Classifier: Programming Language :: Python :: 3.11
Classifier: Programming Language :: Python :: 3.12
Classifier: Programming Language :: Python :: 3.13
Requires-Dist: matplotlib (>=3.1.0,<4.0.0)
Requires-Dist: pandas (>=2.0.0,<3.0.0)
Project-URL: Documentation, https://usepa.github.io/pybeepop/
Project-URL: Repository, https://github.com/USEPA/pybeepop
